LICENSE
es2loki/__init__.py
es2loki/__main__.py
es2loki/aio/__init__.py
es2loki/aio/pool.py
es2loki/aio/tasks.py
es2loki/commands/__init__.py
es2loki/commands/transfer.py
es2loki/es.py
es2loki/loki.py
es2loki/proto/__init__.py
es2loki/proto/gogo.proto
es2loki/proto/gogo_pb2.py
es2loki/proto/logproto.proto
es2loki/proto/logproto_pb2.py
es2loki/state/__init__.py
es2loki/state/db.py
es2loki/state/dummy.py
es2loki/state/types.py
es2loki/utils.py
es2loki-0.1.6.dist-info/METADATA
es2loki-0.1.6.dist-info/WHEEL
es2loki-0.1.6.dist-info/LICENSE
es2loki-0.1.6.dist-info/RECORD
